llama_index/py.typed
llama_index/vector_stores/qdrant/__init__.py
llama_index/vector_stores/qdrant/base.py
llama_index/vector_stores/qdrant/utils.py
llama_index_vector_stores_qdrant-0.8.8.dist-info/METADATA
llama_index_vector_stores_qdrant-0.8.8.dist-info/WHEEL
llama_index_vector_stores_qdrant-0.8.8.dist-info/licenses/LICENSE
llama_index_vector_stores_qdrant-0.8.8.dist-info/RECORD
