Metadata-Version: 2.4
Name: llama-index-vector-stores-qdrant
Version: 0.8.8
Summary: llama-index vector_stores qdrant integration
Author-email: Your Name <you@example.com>
License-Expression: MIT
License-File: LICENSE
Requires-Python: <3.14,>=3.9
Requires-Dist: grpcio<2,>=1.60.0
Requires-Dist: llama-index-core<0.15,>=0.13.0
Requires-Dist: qdrant-client<1.16.0,>=1.7.1
Provides-Extra: fastembed
